pysi/__init__.py
pysi/snippets.py
pysi_kdd-1.0.0.dist-info/licenses/LICENSE
pysi_kdd-1.0.0.dist-info/METADATA
pysi_kdd-1.0.0.dist-info/WHEEL
pysi_kdd-1.0.0.dist-info/top_level.txt
pysi_kdd-1.0.0.dist-info/RECORD
