Metadata-Version: 2.4
Name: pysi-kdd
Version: 1.0.0
Summary: A comprehensive KDD and Data Mining code snippet reference package
Home-page: https://github.com/yourusername/pysi
Author: User
Classifier: Programming Language :: Python :: 3
Classifier: License :: OSI Approved :: MIT License
Classifier: Operating System :: OS Independent
Requires-Python: >=3.6
License-File: LICENSE
Requires-Dist: numpy
Requires-Dist: pandas
Requires-Dist: scikit-learn
Requires-Dist: scipy
Requires-Dist: matplotlib
Requires-Dist: seaborn
Requires-Dist: imbalanced-learn
Requires-Dist: statsmodels
Requires-Dist: xgboost
Requires-Dist: shap
Dynamic: author
Dynamic: classifier
Dynamic: description
Dynamic: description-content-type
Dynamic: home-page
Dynamic: license-file
Dynamic: requires-dist
Dynamic: requires-python
Dynamic: summary
